spider_monitor_flow/__init__.py
spider_monitor_flow/conf.py
spider_monitor_flow/exceptions.py
spider_monitor_flow/log.py
spider_monitor_flow/model.py
spider_monitor_flow/monitor.py
spider_monitor_flow/utils.py
spider_monitor_flow-1.5.dist-info/LICENSE
spider_monitor_flow-1.5.dist-info/METADATA
spider_monitor_flow-1.5.dist-info/WHEEL
spider_monitor_flow-1.5.dist-info/top_level.txt
spider_monitor_flow-1.5.dist-info/RECORD
