Metadata-Version: 2.1
Name: spider-monitor-flow
Version: 1.5
Summary: spider monitor！
Author: simi
Author-email: 1820407818@qq.com
License: UNKNOWN
Platform: UNKNOWN
Classifier: Programming Language :: Python :: 3
Classifier: License :: OSI Approved :: MIT License
Classifier: Operating System :: OS Independent
Requires-Python: >=3
License-File: LICENSE
Requires-Dist: pymongo
Requires-Dist: similib
